[
  {
    "id": "retreat-001",
    "title": "Silent Mountain Retreat",
    "location": "Himalayan Foothills, India",
    "heroImage": "/retreats/retreat-001/hero.webp",
    "gallery": [
      "/retreats/retreat-001/gallery-1.webp",
      "/retreats/retreat-001/gallery-2.webp",
      "/retreats/retreat-001/gallery-3.webp"
    ],
    "operator": {
      "name": "Ananda Collective",
      "bio": "Founded by practitioners who spent 12 years in Himalayan monasteries. Specializes in silent retreats with personalized breath work.",
      "avatar": "/retreats/retreat-001/operator.webp"
    },
    "dates": {
      "start": "2026-10-15",
      "end": "2026-10-22",
      "duration": 7
    },
    "price": {
      "amount": 1850,
      "currency": "USD",
      "includes": [
        "All meals (sattvic, organic)",
        "Private cottage with mountain view",
        "Daily 1:1 guidance sessions",
        "Breath cycle programming",
        "Airport transfers"
      ]
    },
    "capacity": {
      "min": 6,
      "max": 12,
      "current": 8
    },
    "description": "Seven days of noble silence in the Himalayan foothills. Each morning begins with sunrise pranayama on the terrace overlooking snow-capped peaks. The practice blends ancient hatha yoga with modern breath science, creating a container for deep inner work.",
    "highlights": [
      "Complete silence for 7 days",
      "Personalized breath cycle based on your baseline",
      "Mountain sunrise meditation terrace",
      "1:1 guidance with senior practitioners",
      "Organic sattvic meals from the retreat garden"
    ],
    "attestationId": "0xabc123def456789",
    "palette": {
      "primary": "#8B7355",
      "secondary": "#D4A574",
      "accent": "#4A6741"
    }
  },
  {
    "id": "retreat-002",
    "title": "Ocean Breath Intensive",
    "location": "Bali, Indonesia",
    "heroImage": "/retreats/retreat-002/hero.webp",
    "gallery": [
      "/retreats/retreat-002/gallery-1.webp",
      "/retreats/retreat-002/gallery-2.webp",
      "/retreats/retreat-002/gallery-3.webp"
    ],
    "operator": {
      "name": "Maya Suryani",
      "bio": "Balinese yoga teacher and breathwork facilitator with 15 years of experience. Combines traditional Balinese healing with contemporary somatic practices.",
      "avatar": "/retreats/retreat-002/operator.webp"
    },
    "dates": {
      "start": "2026-09-01",
      "end": "2026-09-06",
      "duration": 5
    },
    "price": {
      "amount": 1450,
      "currency": "USD",
      "includes": [
        "Shared villa accommodation",
        "All meals (local organic)",
        "Daily group sessions",
        "Sound healing ceremony",
        "Traditional Balinese blessing"
      ]
    },
    "capacity": {
      "min": 8,
      "max": 16,
      "current": 12
    },
    "description": "Five days of ocean-inspired breath work and vinyasa flow in a clifftop villa overlooking the Indian Ocean. The rhythm of the waves guides each practice, creating a natural metronome for your breath cycle.",
    "highlights": [
      "Clifftop villa with ocean views",
      "Daily sound healing with Tibetan bowls",
      "Traditional Balinese water blessing",
      "Surf-inspired vinyasa sequences",
      "Community of 12 practitioners"
    ],
    "palette": {
      "primary": "#5B8FA8",
      "secondary": "#E8D5B7",
      "accent": "#D4726A"
    }
  },
  {
    "id": "retreat-003",
    "title": "Forest Silence Solo",
    "location": "Pacific Northwest, USA",
    "heroImage": "/retreats/retreat-003/hero.webp",
    "gallery": [
      "/retreats/retreat-003/gallery-1.webp",
      "/retreats/retreat-003/gallery-2.webp",
      "/retreats/retreat-003/gallery-3.webp"
    ],
    "operator": {
      "name": "Cedar Grove Sanctuary",
      "bio": "A small collective of forest-dwelling practitioners offering solo retreats in the old-growth forests of the Pacific Northwest. Minimal infrastructure, maximum solitude.",
      "avatar": "/retreats/retreat-003/operator.webp"
    },
    "dates": {
      "start": "2026-10-01",
      "end": "2026-10-04",
      "duration": 3
    },
    "price": {
      "amount": 750,
      "currency": "USD",
      "includes": [
        "Private forest cabin",
        "Self-catering kitchen",
        "Daily optional check-in call",
        "Trail maps and practice guides",
        "Hot spring access"
      ]
    },
    "capacity": {
      "min": 1,
      "max": 4,
      "current": 1
    },
    "description": "Three days of complete solitude in a hand-built cabin deep in old-growth forest. No group sessions, no scheduled activities—just you, the trees, and your practice. The forest holds space for whatever needs to emerge.",
    "highlights": [
      "Complete solitude (solo retreat)",
      "Hand-built cabin in old-growth forest",
      "Self-paced practice with optional guidance",
      "Natural hot springs 10-minute walk",
      "Minimal digital footprint (no WiFi in cabin)"
    ],
    "attestationId": "0xdef456abc123789",
    "palette": {
      "primary": "#3D5A3D",
      "secondary": "#A8B5A0",
      "accent": "#C9A961"
    }
  },
  {
    "id": "retreat-004",
    "title": "Desert Moon Immersion",
    "location": "Sedona, Arizona, USA",
    "heroImage": "/retreats/retreat-004/hero.webp",
    "gallery": [
      "/retreats/retreat-004/gallery-1.webp",
      "/retreats/retreat-004/gallery-2.webp",
      "/retreats/retreat-004/gallery-3.webp"
    ],
    "operator": {
      "name": "Red Rock Collective",
      "bio": "A group of energy workers and yoga teachers based in Sedona's red rock country. Specializes in lunar cycle practices and earth-based healing modalities.",
      "avatar": "/retreats/retreat-004/operator.webp"
    },
    "dates": {
      "start": "2026-10-10",
      "end": "2026-10-17",
      "duration": 7
    },
    "price": {
      "amount": 2400,
      "currency": "USD",
      "includes": [
        "Luxury eco-lodge accommodation",
        "All meals (chef-prepared)",
        "Daily group ceremonies",
        "Vortex hikes with guides",
        "New moon fire ceremony",
        "Crystal sound bath"
      ]
    },
    "capacity": {
      "min": 10,
      "max": 20,
      "current": 15
    },
    "description": "Seven days aligned with the lunar cycle in Sedona's red rock country. Each day builds toward the new moon fire ceremony, where intentions are released into the desert sky. The practice blends kundalini yoga, breathwork, and earth-based rituals.",
    "highlights": [
      "Lunar cycle alignment (new moon ceremony)",
      "Red rock vortex hikes",
      "Luxury eco-lodge with desert views",
      "Crystal sound healing sessions",
      "Community of 15 practitioners"
    ],
    "palette": {
      "primary": "#C87070",
      "secondary": "#E8C4A0",
      "accent": "#6B4E71"
    }
  },
  {
    "id": "retreat-005",
    "title": "Coastal Flow & Restore",
    "location": "Algarve, Portugal",
    "heroImage": "/retreats/retreat-005/hero.webp",
    "gallery": [
      "/retreats/retreat-005/gallery-1.webp",
      "/retreats/retreat-005/gallery-2.webp",
      "/retreats/retreat-005/gallery-3.webp"
    ],
    "operator": {
      "name": "Ana Rodrigues",
      "bio": "Portuguese yoga teacher and physical therapist. Combines Iyengar precision with restorative practices, creating a balanced approach for bodies in transition.",
      "avatar": "/retreats/retreat-005/operator.webp"
    },
    "dates": {
      "start": "2026-09-20",
      "end": "2026-09-27",
      "duration": 7
    },
    "price": {
      "amount": 1650,
      "currency": "USD",
      "includes": [
        "Beachfront villa (shared room)",
        "All meals (Mediterranean organic)",
        "Daily morning flow + evening restore",
        "Anatomy workshops",
        "Surf lessons (optional)"
      ]
    },
    "capacity": {
      "min": 8,
      "max": 14,
      "current": 10
    },
    "description": "Seven days of balanced practice on Portugal's golden coast. Mornings bring dynamic vinyasa flow to build heat and strength. Evenings offer restorative poses and yoga nidra to integrate and restore. The ocean is your constant companion.",
    "highlights": [
      "Beachfront villa with ocean access",
      "Balanced practice (flow + restore)",
      "Anatomy and alignment workshops",
      "Optional surf lessons",
      "Mediterranean organic cuisine"
    ],
    "palette": {
      "primary": "#6B93A8",
      "secondary": "#F0E5D8",
      "accent": "#E8A87C"
    }
  }
]
